skdatasets/__init__.py
skdatasets/repositories/__init__.py
skdatasets/repositories/aneurisk.py
skdatasets/repositories/base.py
skdatasets/repositories/cran.py
skdatasets/repositories/forex.py
skdatasets/repositories/keel.py
skdatasets/repositories/keras.py
skdatasets/repositories/libsvm.py
skdatasets/repositories/physionet.py
skdatasets/repositories/raetsch.py
skdatasets/repositories/sklearn.py
skdatasets/repositories/uci.py
skdatasets/repositories/ucr.py
skdatasets/tests/__init__.py
skdatasets/tests/repositories/__init__.py
skdatasets/tests/repositories/test_cran.py
skdatasets/tests/repositories/test_forex.py
skdatasets/tests/repositories/test_keel.py
skdatasets/tests/repositories/test_keras.py
skdatasets/tests/repositories/test_libsvm.py
skdatasets/tests/repositories/test_physionet.py
skdatasets/tests/repositories/test_raetsch.py
skdatasets/tests/repositories/test_sklearn.py
skdatasets/tests/repositories/test_uci.py
skdatasets/tests/repositories/test_ucr.py
skdatasets/tests/utils/__init__.py
skdatasets/tests/utils/linear_model.py
skdatasets/tests/utils/run.py
skdatasets/tests/utils/test_estimator.py
skdatasets/tests/utils/test_experiment.py
skdatasets/tests/utils/test_run.py
skdatasets/tests/utils/test_scores.py
skdatasets/utils/__init__.py
skdatasets/utils/estimator.py
skdatasets/utils/experiment.py
skdatasets/utils/scores.py
scikit_datasets-0.2.4.dist-info/LICENSE
scikit_datasets-0.2.4.dist-info/METADATA
scikit_datasets-0.2.4.dist-info/WHEEL
scikit_datasets-0.2.4.dist-info/top_level.txt
scikit_datasets-0.2.4.dist-info/RECORD
