Metadata-Version: 2.1
Name: scikit-datasets
Version: 0.2.4
Summary: Scikit-learn-compatible datasets
Author-email: David Diaz Vico <david.diaz.vico@outlook.com>, Carlos Ramos Carreño <vnmabus@gmail.com>
Maintainer-email: David Diaz Vico <david.diaz.vico@outlook.com>, Carlos Ramos Carreño <vnmabus@gmail.com>
License: MIT License
Project-URL: homepage, https://github.com/daviddiazvico/scikit-datasets
Project-URL: documentation, https://daviddiazvico.github.io/scikit-datasets/
Project-URL: repository, https://github.com/daviddiazvico/scikit-datasets
Project-URL: download, https://github.com/daviddiazvico/scikit-datasets/archive/v0.2.2.tar.gz
Keywords: scikit-learn,datasets,repository,benchmark,Python
Classifier: Intended Audience :: Science/Research
Classifier: Topic :: Scientific/Engineering
Classifier: Programming Language :: Python
Classifier: Programming Language :: Python :: 3
Classifier: Programming Language :: Python :: 3.8
Classifier: Programming Language :: Python :: 3.9
Classifier: Programming Language :: Python :: 3.10
Requires-Python: >=3.8
Provides-Extra: cran
Provides-Extra: forex
Provides-Extra: keel
Provides-Extra: keras
Provides-Extra: physionet
Provides-Extra: utils-estimator
Provides-Extra: utils-experiments
Provides-Extra: utils-scores
Provides-Extra: all
Provides-Extra: test
License-File: LICENSE
